jgdtrans/__init__.py
jgdtrans/dms.py
jgdtrans/error.py
jgdtrans/mesh.py
jgdtrans/par.py
jgdtrans/point.py
jgdtrans/transformer.py
jgdtrans/types.py
jgdtrans-0.3.0.dist-info/METADATA
jgdtrans-0.3.0.dist-info/WHEEL
jgdtrans-0.3.0.dist-info/licenses/LICENSE
jgdtrans-0.3.0.dist-info/RECORD
