Metadata-Version: 2.4
Name: jgdtrans
Version: 0.3.0
Summary: Coordinate Transformer by Gridded Correction Parameter (par file)
Project-URL: Documentation, https://jgdtrans-py.readthedocs.io
Project-URL: Issues, https://github.com/paqira/jgdtrans-py/issues
Project-URL: Source, https://github.com/paqira/jgdtrans-py
Author-email: Kentaro Tatsumi <paqira.2019@gmail.com>
License: MIT
License-File: LICENSE
Keywords: Coordinate Transformation,GIS,HyokoRev,ITRF2014,PatchJGD,PatchJGD(H),PatchJGD(HV),SemiDyna,SemiDynaEXE,TKY2JGD,geonetF3,par file
Classifier: License :: OSI Approved :: MIT License
Classifier: Operating System :: OS Independent
Classifier: Programming Language :: Python
Classifier: Programming Language :: Python :: 3.9
Classifier: Programming Language :: Python :: 3.10
Classifier: Programming Language :: Python :: 3.11
Classifier: Programming Language :: Python :: 3.12
Classifier: Programming Language :: Python :: 3.13
Classifier: Topic :: Scientific/Engineering :: GIS
Requires-Python: >=3.9
Requires-Dist: typing-extensions>=4.9; python_version < '3.11'
